<?xml version="1.0"?>
<RouteScheme xmlns:xsd="http://www.w3.org/2001/XMLSchema" xmlns:xsi="http://www.w3.org/2001/XMLSchema-instance" MaxBlockId="6">
  <Blocks>
    <BlockBase xsi:type="StartBlock">
      <Id>1</Id>
      <BlockTypeId xsi:nil="true" />
      <CustomProperties />
      <ParameterOperations />
    </BlockBase>
    <BlockBase xsi:type="FinishBlock">
      <Id>2</Id>
      <BlockTypeId xsi:nil="true" />
      <CustomProperties />
      <ParameterOperations />
      <UnderReview>false</UnderReview>
      <ReviewAssignmentId>0</ReviewAssignmentId>
    </BlockBase>
  </Blocks>
  <Edges>
    <Edge>
      <Id>0</Id>
      <Source>1</Source>
      <Target>2</Target>
    </Edge>
  </Edges>
  <Layout>
    <BlocksLayout>
      <BlockLayout>
        <BlockId>1</BlockId>
        <Bounds>
          <Location>
            <X>5</X>
            <Y>-152.21679999999998</Y>
          </Location>
          <Size>
            <Width>48</Width>
            <Height>48</Height>
          </Size>
          <X>5</X>
          <Y>-152.21679999999998</Y>
          <Width>48</Width>
          <Height>48</Height>
        </Bounds>
      </BlockLayout>
      <BlockLayout>
        <BlockId>2</BlockId>
        <Bounds>
          <Location>
            <X>5</X>
            <Y>45.783200000000022</Y>
          </Location>
          <Size>
            <Width>48</Width>
            <Height>48</Height>
          </Size>
          <X>5</X>
          <Y>45.783200000000022</Y>
          <Width>48</Width>
          <Height>48</Height>
        </Bounds>
      </BlockLayout>
    </BlocksLayout>
    <EdgesLayout>
      <EdgeLayout>
        <DestinationAnchor>1</DestinationAnchor>
        <EdgeId>0</EdgeId>
        <EndPoint>
          <X>29</X>
          <Y>45.783200000000022</Y>
        </EndPoint>
        <OriginAnchor>3</OriginAnchor>
        <Points>
          <Point>
            <X>29</X>
            <Y>-104.21679999999998</Y>
          </Point>
          <Point>
            <X>29</X>
            <Y>45.783200000000022</Y>
          </Point>
          <Point>
            <X>29</X>
            <Y>45.783200000000022</Y>
          </Point>
        </Points>
        <StartPoint>
          <X>29</X>
          <Y>-104.21679999999998</Y>
        </StartPoint>
      </EdgeLayout>
    </EdgesLayout>
  </Layout>
</RouteScheme>